pytsas/.git/HEAD
pytsas/.git/config
pytsas/.git/description
pytsas/.git/hooks/applypatch-msg.sample
pytsas/.git/hooks/commit-msg.sample
pytsas/.git/hooks/fsmonitor-watchman.sample
pytsas/.git/hooks/post-update.sample
pytsas/.git/hooks/pre-applypatch.sample
pytsas/.git/hooks/pre-commit.sample
pytsas/.git/hooks/pre-merge-commit.sample
pytsas/.git/hooks/pre-push.sample
pytsas/.git/hooks/pre-rebase.sample
pytsas/.git/hooks/pre-receive.sample
pytsas/.git/hooks/prepare-commit-msg.sample
pytsas/.git/hooks/push-to-checkout.sample
pytsas/.git/hooks/update.sample
pytsas/.git/info/exclude
pytsas/__init__.py
pytsas/aggregate/__init__.py
pytsas/base.py
pytsas/event/__init__.py
pytsas/event/detector.py
pytsas/event/timeframe.py
pytsas/event/trigger.py
pytsas/menu.py
pytsas-0.0.1.dist-info/LICENSE
pytsas-0.0.1.dist-info/WHEEL
pytsas-0.0.1.dist-info/METADATA
pytsas-0.0.1.dist-info/RECORD
