Metadata-Version: 2.1
Name: pytsas
Version: 0.0.1
Summary: Package for python time-series analyses
License: MIT
Author: mk.fschr
Author-email: mike.robin.fischer@web.de
Requires-Python: >=3.8,<4.0
Classifier: License :: OSI Approved :: MIT License
Classifier: Programming Language :: Python :: 3
Classifier: Programming Language :: Python :: 3.10
Classifier: Programming Language :: Python :: 3.8
Classifier: Programming Language :: Python :: 3.9
Requires-Dist: pandas (>=1.4.3,<2.0.0)
